<?xml version="1.0" encoding="utf-8" standalone="no" ?>
<modDesc descVersion="40">
    <author>SCFmod</author>
    <version>1.0.0.0</version>
    <title>
        <en>SCFmod Toolkit</en>
    </title>
    <description>
        <en><![CDATA[Toolkit for scripting/testing]]></en>
    </description>
    <iconFilename>store.png</iconFilename>
    <multiplayer supported="true" />
    <extraSourceFiles>
        <sourceFile filename="lib/30log.lua" />
        <sourceFile filename="IClass.lua" />
        <sourceFile filename="functions.lua" />
        <sourceFile filename="InspectTable.lua" />

        <!--<sourceFile filename="TraverseTable.lua" />-->
        <!--<sourceFile filename="toolkit.lua" />-->
    </extraSourceFiles>
</modDesc>
